<?xml version="1.0" encoding="utf-8"?>
  <GlobalConfiguration>
    <ConfigurationDirectory>{basedir}/../../src/main/resources/config</ConfigurationDirectory>
	<ProjectDirectory>{basedir}/../../src/main/resources/test</ProjectDirectory>
    <PluginsDirectory>{basedir}/plugins</PluginsDirectory>
    <PluginLoaders>
        net.sf.testium.plugins.SurefireReportPlugin;
        net.sf.testium.plugins.ShellTestPlugin;
        net.sf.testium.plugins.SutControlPlugin;
<!-- 
        net.sf.testium.plugins.PerlTestPlugin;
        net.sf.testium.plugins.SoapuiPlugin;
 -->
		net.sf.testium.plugins.SeleniumPlugin
   </PluginLoaders>
<!-- 
    <OsgiPlugins>
    	<OsgiPlugin>
    		<name>net.sf.testium.plugins.ExamplePlugin</name>
    		<url>file:{basedir}\plugins\testium-example-plugin-0.0.1-SNAPSHOT.jar</url>
    	</OsgiPlugin>
    	<OsgiPlugin>
    		<name>net.sf.testium.plugins.SoapuiPlugin</name>
    		<url>file:{basedir}\plugins\testium-soapui-plugin-0.4.1-SNAPSHOT.jar</url>
    	</OsgiPlugin>
 -->
<!-- 
    	<OsgiPlugin>
    		<name>net.sf.testium.plugins.TryoutPlugin</name>
    		<url>file:{basedir}\plugins\testium-tryout-plugin-0.0.1-SNAPSHOT.jar</url>
    	</OsgiPlugin>
 -->
 <!-- 
    </OsgiPlugins>
 -->
    <DefaultUserConfigurationFile>.testautomation</DefaultUserConfigurationFile>
    <!--TraceEnabled>false</TraceEnabled-->
    <TraceDepth>10</TraceDepth>
    <TraceClass>net.sf.testium.Main</TraceClass>
    <TraceLevel>ALL</TraceLevel>
    <!-- 
		0: HIGH,
		1: EXEC,
		2: EXEC_PLUS,
		3: EXEC_UTIL,
		4: SUITE,
		5: CONSTRUCTOR,
		6: UTIL,
		7: SETTER,
		8: GETTER,
		9: ALL
	-->
    <TestEnvironment>System Test</TestEnvironment>
<!-- 
	<Interfaces>
		<Interface name="Default">
		    <CustomStepDefinitionsLink>{basedir}\keywords\keyword_with_optional_parameter.xml</CustomStepDefinitionsLink>
		</Interface>
	</Interfaces>
 -->
  </GlobalConfiguration>
